applib/__init__.py
appget_lib-0.1.0.dev1.dist-info/LICENSE
appget_lib-0.1.0.dev1.dist-info/METADATA
appget_lib-0.1.0.dev1.dist-info/WHEEL
appget_lib-0.1.0.dev1.dist-info/top_level.txt
appget_lib-0.1.0.dev1.dist-info/RECORD
