Metadata-Version: 2.1
Name: appget-lib
Version: 0.1.0.dev1
Summary: A package library management tool
Author-email: Example Author <author@example.com>
Maintainer-email: "A. Great Maintainer" <maintainer@example.com>
License: MIT License
Project-URL: Homepage, https://github.com/lonelypale/applib
Project-URL: Issues, https://github.com/lonelypale/applib/issues
Keywords: applib,appget,setuptools,development
Classifier: Programming Language :: Python :: 3
Classifier: License :: OSI Approved :: MIT License
Classifier: Operating System :: OS Independent
Requires-Python: >=3.9
License-File: LICENSE
Requires-Dist: appget
